{
  "records": [
    {
      "id": -69,
      "UserID": "usr_b1e0d307-038d-45d2-90b5-f999b7ff3e4f",
      "Tag": [ "<color=#FFFFFF>voids is sexy fr fr</color>", "<color=#ff0000>will tickle ur butthole</color>" ],
      "PlateBigText": "<b><color=#FFFFFF>OWNER</color></b>",
      "Malicious": false,
      "Active": true,
      "TextActive": true,
      "BigTextActive": true,
      "Size": "<size=58>"
    },
    {
      "id": 100,
      "UserID": "usr_ad09cb62-1cd5-4d8f-a99a-29a2b6508e74",
      "Tag": [ "<color=#FFFFFF>funny helper man</color>", "<color=#ff0000>will tickle ur penis</color>" ],
      "PlateBigText": "<b><color=#FFFFFF>OWNER</color></b>",
      "Malicious": false,
      "Active": true,
      "TextActive": true,
      "BigTextActive": false,
      "Size": "<size=58>"
    }
  ]
}
